<annotation>
  <folder>images</folder>
  <filename>20190111GOPR9025_2.jpg</filename>
  <path>/home/elcymon/litter-detection/mobilenetSSD/litter/images/20190111GOPR9025_2.jpg</path>
  <source>
    <database>Unknown</database>
  </source>
  <size>
    <width>1920</width>
    <height>1080</height>
    <depth>3</depth>
  </size>
  <segmented>0</segmented>
  <object>
    <name>litter</name>
    <pose>Unspecified</pose>
    <truncated>0</truncated>
    <difficult>0</difficult>
    <bndbox>
      <xmin>1680</xmin>
      <ymin>268</ymin>
      <xmax>1724</xmax>
      <ymax>326</ymax>
    </bndbox>
  </object>
  <object>
    <name>litter</name>
    <pose>Unspecified</pose>
    <truncated>0</truncated>
    <difficult>0</difficult>
    <bndbox>
      <xmin>1667</xmin>
      <ymin>206</ymin>
      <xmax>1696</xmax>
      <ymax>222</ymax>
    </bndbox>
  </object>
  <object>
    <name>litter</name>
    <pose>Unspecified</pose>
    <truncated>0</truncated>
    <difficult>0</difficult>
    <bndbox>
      <xmin>1692</xmin>
      <ymin>142</ymin>
      <xmax>1724</xmax>
      <ymax>159</ymax>
    </bndbox>
  </object>
  <object>
    <name>litter</name>
    <pose>Unspecified</pose>
    <truncated>0</truncated>
    <difficult>0</difficult>
    <bndbox>
      <xmin>1686</xmin>
      <ymin>162</ymin>
      <xmax>1715</xmax>
      <ymax>186</ymax>
    </bndbox>
  </object>
  <object>
    <name>litter</name>
    <pose>Unspecified</pose>
    <truncated>0</truncated>
    <difficult>0</difficult>
    <bndbox>
      <xmin>1561</xmin>
      <ymin>93</ymin>
      <xmax>1582</xmax>
      <ymax>105</ymax>
    </bndbox>
  </object>
  <object>
    <name>litter</name>
    <pose>Unspecified</pose>
    <truncated>0</truncated>
    <difficult>0</difficult>
    <bndbox>
      <xmin>1463</xmin>
      <ymin>109</ymin>
      <xmax>1501</xmax>
      <ymax>129</ymax>
    </bndbox>
  </object>
  <object>
    <name>litter</name>
    <pose>Unspecified</pose>
    <truncated>0</truncated>
    <difficult>0</difficult>
    <bndbox>
      <xmin>1428</xmin>
      <ymin>61</ymin>
      <xmax>1442</xmax>
      <ymax>70</ymax>
    </bndbox>
  </object>
  <object>
    <name>litter</name>
    <pose>Unspecified</pose>
    <truncated>0</truncated>
    <difficult>0</difficult>
    <bndbox>
      <xmin>1410</xmin>
      <ymin>63</ymin>
      <xmax>1425</xmax>
      <ymax>73</ymax>
    </bndbox>
  </object>
  <object>
    <name>litter</name>
    <pose>Unspecified</pose>
    <truncated>0</truncated>
    <difficult>0</difficult>
    <bndbox>
      <xmin>1160</xmin>
      <ymin>42</ymin>
      <xmax>1181</xmax>
      <ymax>55</ymax>
    </bndbox>
  </object>
  <object>
    <name>litter</name>
    <pose>Unspecified</pose>
    <truncated>0</truncated>
    <difficult>0</difficult>
    <bndbox>
      <xmin>1032</xmin>
      <ymin>32</ymin>
      <xmax>1058</xmax>
      <ymax>40</ymax>
    </bndbox>
  </object>
  <object>
    <name>litter</name>
    <pose>Unspecified</pose>
    <truncated>0</truncated>
    <difficult>0</difficult>
    <bndbox>
      <xmin>1009</xmin>
      <ymin>36</ymin>
      <xmax>1031</xmax>
      <ymax>45</ymax>
    </bndbox>
  </object>
  <object>
    <name>litter</name>
    <pose>Unspecified</pose>
    <truncated>0</truncated>
    <difficult>0</difficult>
    <bndbox>
      <xmin>1036</xmin>
      <ymin>44</ymin>
      <xmax>1061</xmax>
      <ymax>59</ymax>
    </bndbox>
  </object>
  <object>
    <name>litter</name>
    <pose>Unspecified</pose>
    <truncated>0</truncated>
    <difficult>0</difficult>
    <bndbox>
      <xmin>977</xmin>
      <ymin>63</ymin>
      <xmax>1002</xmax>
      <ymax>76</ymax>
    </bndbox>
  </object>
  <object>
    <name>litter</name>
    <pose>Unspecified</pose>
    <truncated>0</truncated>
    <difficult>0</difficult>
    <bndbox>
      <xmin>1066</xmin>
      <ymin>78</ymin>
      <xmax>1096</xmax>
      <ymax>95</ymax>
    </bndbox>
  </object>
  <object>
    <name>litter</name>
    <pose>Unspecified</pose>
    <truncated>0</truncated>
    <difficult>0</difficult>
    <bndbox>
      <xmin>1150</xmin>
      <ymin>121</ymin>
      <xmax>1198</xmax>
      <ymax>144</ymax>
    </bndbox>
  </object>
</annotation>
