<annotation>
  <folder>images</folder>
  <filename>20190111GOPR9023_6.jpg</filename>
  <path>/home/elcymon/litter-detection/mobilenetSSD/litter/images/20190111GOPR9023_6.jpg</path>
  <source>
    <database>Unknown</database>
  </source>
  <size>
    <width>1920</width>
    <height>1080</height>
    <depth>3</depth>
  </size>
  <segmented>0</segmented>
  <object>
    <name>litter</name>
    <pose>Unspecified</pose>
    <truncated>0</truncated>
    <difficult>0</difficult>
    <bndbox>
      <xmin>1669</xmin>
      <ymin>134</ymin>
      <xmax>1699</xmax>
      <ymax>152</ymax>
    </bndbox>
  </object>
  <object>
    <name>litter</name>
    <pose>Unspecified</pose>
    <truncated>0</truncated>
    <difficult>0</difficult>
    <bndbox>
      <xmin>1645</xmin>
      <ymin>92</ymin>
      <xmax>1671</xmax>
      <ymax>104</ymax>
    </bndbox>
  </object>
  <object>
    <name>litter</name>
    <pose>Unspecified</pose>
    <truncated>0</truncated>
    <difficult>0</difficult>
    <bndbox>
      <xmin>1340</xmin>
      <ymin>96</ymin>
      <xmax>1372</xmax>
      <ymax>135</ymax>
    </bndbox>
  </object>
  <object>
    <name>litter</name>
    <pose>Unspecified</pose>
    <truncated>0</truncated>
    <difficult>0</difficult>
    <bndbox>
      <xmin>1297</xmin>
      <ymin>28</ymin>
      <xmax>1329</xmax>
      <ymax>46</ymax>
    </bndbox>
  </object>
  <object>
    <name>litter</name>
    <pose>Unspecified</pose>
    <truncated>0</truncated>
    <difficult>0</difficult>
    <bndbox>
      <xmin>1200</xmin>
      <ymin>37</ymin>
      <xmax>1227</xmax>
      <ymax>54</ymax>
    </bndbox>
  </object>
  <object>
    <name>litter</name>
    <pose>Unspecified</pose>
    <truncated>0</truncated>
    <difficult>0</difficult>
    <bndbox>
      <xmin>1243</xmin>
      <ymin>5</ymin>
      <xmax>1266</xmax>
      <ymax>20</ymax>
    </bndbox>
  </object>
  <object>
    <name>litter</name>
    <pose>Unspecified</pose>
    <truncated>0</truncated>
    <difficult>0</difficult>
    <bndbox>
      <xmin>1019</xmin>
      <ymin>27</ymin>
      <xmax>1053</xmax>
      <ymax>41</ymax>
    </bndbox>
  </object>
  <object>
    <name>litter</name>
    <pose>Unspecified</pose>
    <truncated>0</truncated>
    <difficult>0</difficult>
    <bndbox>
      <xmin>760</xmin>
      <ymin>113</ymin>
      <xmax>827</xmax>
      <ymax>149</ymax>
    </bndbox>
  </object>
  <object>
    <name>litter</name>
    <pose>Unspecified</pose>
    <truncated>0</truncated>
    <difficult>0</difficult>
    <bndbox>
      <xmin>649</xmin>
      <ymin>85</ymin>
      <xmax>686</xmax>
      <ymax>110</ymax>
    </bndbox>
  </object>
  <object>
    <name>litter</name>
    <pose>Unspecified</pose>
    <truncated>0</truncated>
    <difficult>0</difficult>
    <bndbox>
      <xmin>695</xmin>
      <ymin>46</ymin>
      <xmax>735</xmax>
      <ymax>63</ymax>
    </bndbox>
  </object>
  <object>
    <name>litter</name>
    <pose>Unspecified</pose>
    <truncated>0</truncated>
    <difficult>0</difficult>
    <bndbox>
      <xmin>782</xmin>
      <ymin>13</ymin>
      <xmax>814</xmax>
      <ymax>32</ymax>
    </bndbox>
  </object>
  <object>
    <name>litter</name>
    <pose>Unspecified</pose>
    <truncated>0</truncated>
    <difficult>0</difficult>
    <bndbox>
      <xmin>827</xmin>
      <ymin>5</ymin>
      <xmax>868</xmax>
      <ymax>16</ymax>
    </bndbox>
  </object>
  <object>
    <name>litter</name>
    <pose>Unspecified</pose>
    <truncated>0</truncated>
    <difficult>0</difficult>
    <bndbox>
      <xmin>915</xmin>
      <ymin>5</ymin>
      <xmax>936</xmax>
      <ymax>18</ymax>
    </bndbox>
  </object>
</annotation>
